[
    {
        "id": "1",
        "group": "Site",
        "key": "site.name",
        "display_name": "Name",
        "value": "Bdtask",
        "type": "text",
        "details": null,
        "note": null,
        "order": "1",
        "created_at": "2023-03-21 12:00:12",
        "updated_at": "2023-03-21 12:00:12"
    },
    {
        "id": "2",
        "group": "Site",
        "key": "site.description",
        "display_name": "Description",
        "value": "Want to study abroad ? Get free expert advice and information on colleges, courses, exams, admission, student visa, and application process to study overseas.",
        "type": "text_area",
        "details": null,
        "note": null,
        "order": "2",
        "created_at": "2023-03-21 12:00:12",
        "updated_at": "2023-03-21 12:00:12"
    },
    {
        "id": "3",
        "group": "Site",
        "key": "site.url",
        "display_name": "Site Url",
        "value": "https:\/\/www.bdtask.com",
        "type": "text",
        "details": null,
        "note": null,
        "order": "3",
        "created_at": "2023-03-21 12:00:12",
        "updated_at": "2023-03-21 12:00:12"
    },
    {
        "id": "4",
        "group": "Site",
        "key": "site.logo_light",
        "display_name": "Logo White",
        "value": null,
        "type": "image",
        "details": null,
        "note": "Default image size 205x60",
        "order": "4",
        "created_at": "2023-03-21 12:00:12",
        "updated_at": "2023-03-21 12:00:12"
    },
    {
        "id": "5",
        "group": "Site",
        "key": "site.logo_black",
        "display_name": "Logo Black",
        "value": null,
        "type": "image",
        "details": null,
        "note": "Default image size 205x60",
        "order": "4",
        "created_at": "2023-03-21 12:00:12",
        "updated_at": "2023-03-21 12:00:12"
    },
    {
        "id": "6",
        "group": "Site",
        "key": "site.favicon",
        "display_name": "Favicon",
        "value": null,
        "type": "image",
        "details": null,
        "note": "Default image size 68x68",
        "order": "8",
        "created_at": "2023-03-21 12:00:12",
        "updated_at": "2023-03-21 12:00:12"
    },
    {
        "id": "7",
        "group": "Contact",
        "key": "contact.phn",
        "display_name": "Phone",
        "value": "+880 1xxx xxx xxx",
        "type": "text",
        "details": null,
        "note": null,
        "order": "1",
        "created_at": "2023-03-21 12:00:12",
        "updated_at": "2023-03-21 12:00:12"
    },
    {
        "id": "8",
        "group": "Contact",
        "key": "contact.email",
        "display_name": "Email",
        "value": "info@xxxxx.xxxx",
        "type": "text",
        "details": null,
        "note": null,
        "order": "2",
        "created_at": "2023-03-21 12:00:12",
        "updated_at": "2023-03-21 12:00:12"
    },
    {
        "id": "9",
        "group": "Contact",
        "key": "contact.address",
        "display_name": "Address",
        "value": "xxxx,xxxx,xxxx-xxx",
        "type": "text",
        "details": null,
        "note": null,
        "order": "3",
        "created_at": "2023-03-21 12:00:12",
        "updated_at": "2023-03-21 12:00:12"
    },
    {
        "id": "16",
        "group": "Appearance",
        "key": "appearance.auth_img",
        "display_name": "Authentication image",
        "value": null,
        "type": "image",
        "details": "[]",
        "note": null,
        "order": "1",
        "created_at": "2023-03-23 10:45:32",
        "updated_at": "2023-03-23 10:49:34"
    },
    {
        "id": "17",
        "group": "Appearance",
        "key": "appearance.auth_quote_title",
        "display_name": "Authentication Page Quote Title",
        "value": "Top Notch Stock Resources",
        "type": "text",
        "details": "[]",
        "note": null,
        "order": "2",
        "created_at": "2023-03-23 10:51:08",
        "updated_at": "2023-03-23 10:54:13"
    },
    {
        "id": "18",
        "group": "Appearance",
        "key": "appearance.auth_quote",
        "display_name": "Authentication Page Quote",
        "value": "Today, we create innovative solutions to the challenges that consumers face in both their everyday lives and events.",
        "type": "text_area",
        "details": "[]",
        "note": null,
        "order": "3",
        "created_at": "2023-03-23 10:55:02",
        "updated_at": "2023-03-23 10:55:18"
    },
    {
        "id": "19",
        "group": "Site",
        "key": "site.header_tagline",
        "display_name": "Site Header Tag Line",
        "value": "<p>Welcome to <span class=\"fw-bold\">Aiguru Dashboard<\/span><\/p><p>Empowering your knowledge with <b>AI Guru.<\/b><\/p> <p>Discover the potential of AI with <b>AI Guru.<\/b><\/p> <p>Unlock the power of AI with <b>AI Guru.<\/b><\/p> <p>Your guide to mastering AI - <b>AI Guru.<\/b><\/p> <p> Experience the future of learning with <b>AI Guru.<\/b><\/p> <p>Transform your skills with <b>AI Guru.<\/b><\/p> <p>Empower your career with <b>AI Guru.<\/b><\/p> <p>Learn the skills of tomorrow with <b>AI Guru.<\/b><\/p> <p>Your personal AI tutor - <b>AI Guru.<\/b><\/p> <p>AI made easy with <b>AI Guru.<\/b><\/p>",
        "type": "code_editor",
        "details": "{\"theme\": \"dark\", \"language\": \"html\"}",
        "note": null,
        "order": "9",
        "created_at": "2023-03-29 06:07:40",
        "updated_at": "2023-03-29 06:11:13"
    }
]
